RELEASES.md
aio_taginfo/__init__.py
aio_taginfo/api/__init__.py
aio_taginfo/api/v4/__init__.py
aio_taginfo/api/v4/_internal.py
aio_taginfo/api/v4/key/__init__.py
aio_taginfo/api/v4/key/chronology.py
aio_taginfo/api/v4/key/combinations.py
aio_taginfo/api/v4/key/distribution/__init__.py
aio_taginfo/api/v4/key/distribution/nodes.py
aio_taginfo/api/v4/key/distribution/ways.py
aio_taginfo/api/v4/key/overview.py
aio_taginfo/api/v4/key/prevalent_values.py
aio_taginfo/api/v4/key/projects.py
aio_taginfo/api/v4/key/similar.py
aio_taginfo/api/v4/key/stats.py
aio_taginfo/api/v4/key/values.py
aio_taginfo/api/v4/key/wiki_pages.py
aio_taginfo/api/v4/keys/__init__.py
aio_taginfo/api/v4/keys/all.py
aio_taginfo/api/v4/keys/similar.py
aio_taginfo/api/v4/keys/wiki_pages.py
aio_taginfo/api/v4/keys/without_wiki_page.py
aio_taginfo/api/v4/languages.py
aio_taginfo/api/v4/project/__init__.py
aio_taginfo/api/v4/project/icon.py
aio_taginfo/api/v4/project/tags.py
aio_taginfo/api/v4/projects/__init__.py
aio_taginfo/api/v4/projects/all.py
aio_taginfo/api/v4/projects/keys.py
aio_taginfo/api/v4/projects/tags.py
aio_taginfo/api/v4/relation/__init__.py
aio_taginfo/api/v4/relation/projects.py
aio_taginfo/api/v4/relation/roles.py
aio_taginfo/api/v4/relation/stats.py
aio_taginfo/api/v4/relation/wiki_pages.py
aio_taginfo/api/v4/relations/__init__.py
aio_taginfo/api/v4/relations/all.py
aio_taginfo/api/v4/search/__init__.py
aio_taginfo/api/v4/search/by_key_and_value.py
aio_taginfo/api/v4/search/by_keyword.py
aio_taginfo/api/v4/search/by_role.py
aio_taginfo/api/v4/search/by_value.py
aio_taginfo/api/v4/site/__init__.py
aio_taginfo/api/v4/site/config/__init__.py
aio_taginfo/api/v4/site/config/geodistribution.py
aio_taginfo/api/v4/site/info.py
aio_taginfo/api/v4/site/sources.py
aio_taginfo/api/v4/tag/__init__.py
aio_taginfo/api/v4/tag/chronology.py
aio_taginfo/api/v4/tag/combinations.py
aio_taginfo/api/v4/tag/distribution/__init__.py
aio_taginfo/api/v4/tag/distribution/nodes.py
aio_taginfo-0.4.0.dist-info/LICENSE
aio_taginfo-0.4.0.dist-info/METADATA
aio_taginfo-0.4.0.dist-info/WHEEL
aio_taginfo-0.4.0.dist-info/RECORD
