Metadata-Version: 2.1
Name: aio-taginfo
Version: 0.4.0
Summary: Async client for the OpenStreetMap taginfo API
Home-page: https://github.com/timwie/aio-taginfo
License: MIT
Keywords: geospatial,gis,openstreetmap,osm,taginfo,spatial-analysis,spatial-data
Author: Tim Wiechers
Author-email: mail@timwie.dev
Requires-Python: >=3.10,<4.0
Classifier: Development Status :: 3 - Alpha
Classifier: Framework :: AsyncIO
Classifier: Framework :: aiohttp
Classifier: Intended Audience :: Developers
Classifier: Intended Audience :: Science/Research
Classifier: License :: OSI Approved :: MIT License
Classifier: Operating System :: OS Independent
Classifier: Programming Language :: Python :: 3
Classifier: Programming Language :: Python :: 3.10
Classifier: Programming Language :: Python :: 3.11
Classifier: Programming Language :: Python :: 3.12
Classifier: Topic :: Internet :: WWW/HTTP
Classifier: Topic :: Scientific/Engineering :: GIS
Classifier: Topic :: Software Development :: Libraries :: Python Modules
Classifier: Typing :: Typed
Requires-Dist: aiohttp[speedups] (>=3.9,<4.0)
Requires-Dist: pydantic (>=2.4,<3.0)
Project-URL: Documentation, https://www.timwie.dev/aio-taginfo/
Project-URL: Repository, https://github.com/timwie/aio-taginfo
Project-URL: Release Notes, https://github.com/timwie/aio-taginfo/blob/main/RELEASES.md
Project-URL: Test Coverage, https://codecov.io/gh/timwie/aio-taginfo
